photons_interactor/__init__.py
photons_interactor/addon.py
photons_interactor/assets.py
photons_interactor/errors.py
photons_interactor/executor.py
photons_interactor/options.py
photons_interactor/server.py
photons_interactor/commander/__init__.py
photons_interactor/commander/default_fields.py
photons_interactor/commander/errors.py
photons_interactor/commander/helpers.py
photons_interactor/commander/spec_description.py
photons_interactor/commander/store.py
photons_interactor/commander/test_helpers.py
photons_interactor/commander/tiles.py
photons_interactor/commander/commands/__init__.py
photons_interactor/commander/commands/animations.py
photons_interactor/commander/commands/base.py
photons_interactor/commander/commands/control.py
photons_interactor/commander/commands/scenes.py
photons_interactor/commander/commands/tiles.py
photons_interactor/database/__init__.py
photons_interactor/database/connection.py
photons_interactor/database/database.py
photons_interactor/database/db_queue.py
photons_interactor/database/__pycache__/__init__.cpython-37.pyc
photons_interactor/database/__pycache__/__init__.cpython-38.pyc
photons_interactor/database/__pycache__/connection.cpython-37.pyc
photons_interactor/database/__pycache__/connection.cpython-38.pyc
photons_interactor/database/__pycache__/database.cpython-37.pyc
photons_interactor/database/__pycache__/database.cpython-38.pyc
photons_interactor/database/__pycache__/db_queue.cpython-37.pyc
photons_interactor/database/__pycache__/db_queue.cpython-38.pyc
photons_interactor/database/__pycache__/test_helpers.cpython-37-pytest-5.3.1.pyc
photons_interactor/database/__pycache__/test_helpers.cpython-37.pyc
photons_interactor/database/migrations/script.py.mako
photons_interactor/database/migrations/versions/119f5f1434f7_add_scenes.py
photons_interactor/database/migrations/versions/aab549c5cdbd_add_scene_info.py
photons_interactor/database/migrations/versions/__pycache__/119f5f1434f7_add_scenes.cpython-37.pyc
photons_interactor-0.6.0.dist-info/LICENSE
photons_interactor-0.6.0.dist-info/METADATA
photons_interactor-0.6.0.dist-info/WHEEL
photons_interactor-0.6.0.dist-info/entry_points.txt
photons_interactor-0.6.0.dist-info/top_level.txt
photons_interactor-0.6.0.dist-info/RECORD
