Metadata-Version: 2.1
Name: photons-interactor
Version: 0.6.0
Summary: A server for interacting with LIFX lights over the LAN
Home-page: http://github.com/delfick/photons-interactor
Author: Stephen Moore
Author-email: delfick755@gmail.com
License: cc-by-nc-sa-4.0
Keywords: lifx photons
Platform: UNKNOWN
Requires-Python: >= 3.6
Requires-Dist: delfick-project (==0.7.3)
Requires-Dist: lifx-photons-core (==0.24.5)
Requires-Dist: tornado (==5.1.1)
Requires-Dist: SQLAlchemy (==1.3.3)
Requires-Dist: alembic (==1.3.2)
Requires-Dist: whirlwind-web (==0.6)
Provides-Extra: tests
Requires-Dist: noseOfYeti (==1.9.1) ; extra == 'tests'
Requires-Dist: asynctest (==0.12.2) ; extra == 'tests'
Requires-Dist: pytest (==5.3.1) ; extra == 'tests'
Requires-Dist: alt-pytest-asyncio (==0.5.1) ; extra == 'tests'
